rhinomcp/__init__.py
rhinomcp/server.py
rhinomcp/prompts/assert_general_strategy.py
rhinomcp/static/rhinoscriptsyntax.py
rhinomcp/tools/create_layer.py
rhinomcp/tools/create_object.py
rhinomcp/tools/create_objects.py
rhinomcp/tools/delete_layer.py
rhinomcp/tools/delete_object.py
rhinomcp/tools/execute_rhinoscript_python_code.py
rhinomcp/tools/get_document_info.py
rhinomcp/tools/get_object_info.py
rhinomcp/tools/get_or_set_current_layer.py
rhinomcp/tools/get_rhinoscript_python_code_guide.py
rhinomcp/tools/get_rhinoscript_python_function_names.py
rhinomcp/tools/get_selected_objects_info.py
rhinomcp/tools/modify_object.py
rhinomcp/tools/modify_objects.py
rhinomcp/tools/select_objects.py
iflow_mcp_jingcheng_chen_rhinomcp-0.1.3.6.dist-info/METADATA
iflow_mcp_jingcheng_chen_rhinomcp-0.1.3.6.dist-info/WHEEL
iflow_mcp_jingcheng_chen_rhinomcp-0.1.3.6.dist-info/entry_points.txt
iflow_mcp_jingcheng_chen_rhinomcp-0.1.3.6.dist-info/top_level.txt
iflow_mcp_jingcheng_chen_rhinomcp-0.1.3.6.dist-info/RECORD
